setup.py
vildvittra/__init__.py
vildvittra/old.py
vildvittra/vildvittra.py
vildvittra.egg-info/PKG-INFO
vildvittra.egg-info/SOURCES.txt
vildvittra.egg-info/dependency_links.txt
vildvittra.egg-info/requires.txt
vildvittra.egg-info/top_level.txt