Metadata-Version: 1.0
Name: vildvittra
Version: 0.0.3
Summary: Till mit gos Egil.
Home-page: UNKNOWN
Author: UNKNOWN
Author-email: UNKNOWN
License: This code is in the public domain
Keywords: vild vittra kleosa vacker vackra
Platform: UNKNOWN
